xmq/__init__.py
xmq/register_manager.py
xmq/xmq_server.py
xmq/brokers/__init__.py
xmq/brokers/simple_queue.py
xmq/brokers/simple_topic.py
xmq/brokers/unique_key_queue.py
xmq/brokers/unique_key_topic.py
xmq/clients/__init__.py
xmq/clients/simple_client.py
xmq/clients/unique_key_client.py
xmq/common/__init__.py
xmq/common/msg.py
xmq/common/protocol.py
xmq/common/tools.py
xmq-0.0.3.dist-info/LICENSE
xmq-0.0.3.dist-info/METADATA
xmq-0.0.3.dist-info/WHEEL
xmq-0.0.3.dist-info/top_level.txt
xmq-0.0.3.dist-info/RECORD
